dfm_tools/__init__.py
dfm_tools/bathymetry.py
dfm_tools/coastlines.py
dfm_tools/data.py
dfm_tools/deprecated_functions.py
dfm_tools/download.py
dfm_tools/errors.py
dfm_tools/get_nc.py
dfm_tools/get_nc_helpers.py
dfm_tools/hydrolib_helpers.py
dfm_tools/interpolate_grid2bnd.py
dfm_tools/linebuilder.py
dfm_tools/meshkernel_helpers.py
dfm_tools/modelbuilder.py
dfm_tools/modplot.py
dfm_tools/observations.py
dfm_tools/settings.py
dfm_tools/xarray_helpers.py
dfm_tools/xugrid_helpers.py
dfm_tools-0.44.0.dist-info/licenses/LICENSE
dfm_tools-0.44.0.dist-info/METADATA
dfm_tools-0.44.0.dist-info/WHEEL
dfm_tools-0.44.0.dist-info/top_level.txt
dfm_tools-0.44.0.dist-info/RECORD
